<filesystem>

	<folder name="Programming" size="1000">
		<folder name="Software" size="2000">
			<file name="Java.doc" size="1000"></file>
			<file name="Python.doc" size="3000"></file>
			<folder name="Design" size="1000">
				<file name="Photoshop.jpg" size="5000"></file>
				<folder name="EmptyFolder1" size="4000">
				</folder>
				<folder name="EmptyFolder2" size="3000">
					<folder name="EmptyFolder1" size="2000">
					</folder>
					<folder name="EmptyFolder2" size="1000">
						<folder name="EmptyFolder1" size="4000">
						</folder>
						<folder name="EmptyFolder2" size="3000">
						</folder>
					</folder>
				</folder>
			</folder>
		</folder>
		<file name="design.png" size="5000"></file>
	</folder>

	<folder name="Engineering" size="4000">
		<folder name="Mechanical" size="2000">
			<file name="Robotics.doc" size="6000"></file>
			<file name="Thermodynamics.doc" size="2000"></file>
			<folder name="CAD_Design" size="4000">
				<file name="AutoCAD.jpg" size="4000"></file>
				<folder name="EmptyFolder1" size="2000">
				</folder>
				<folder name="EmptyFolder2" size="3000">
				</folder>
			</folder>
			<folder name="EmptyFolder1" size="1000">
			</folder>
			<folder name="EmptyFolder2" size="3000">
			</folder>
		</folder>
		<file name="Blueprint.png" size="2000"></file>
	</folder>


	<folder name="Lectures" size="2000">
		<file name="Algorithms.doc" size="2000"></file>
		<file name="Data.doc" size="3000"></file>
		<file name="iot.doc" size="5000"></file>
		<folder name="EmptyFolder1" size="1000">
		</folder>
		<folder name="EmptyFolder2" size="4000">
		</folder>
	
	</folder>
	
</filesystem>